s_boxes_package_Phnx/__init__.py
s_boxes_package_Phnx/s_boxes.py
s_boxes_package_Phnx-0.0.2.dist-info/LICENSE
s_boxes_package_Phnx-0.0.2.dist-info/METADATA
s_boxes_package_Phnx-0.0.2.dist-info/WHEEL
s_boxes_package_Phnx-0.0.2.dist-info/top_level.txt
s_boxes_package_Phnx-0.0.2.dist-info/RECORD
